praktikum_nlp/__init__.py
praktikum_nlp/uir.py
praktikum_nlp-0.1.4.dist-info/METADATA
praktikum_nlp-0.1.4.dist-info/WHEEL
praktikum_nlp-0.1.4.dist-info/top_level.txt
praktikum_nlp-0.1.4.dist-info/RECORD
