Metadata-Version: 2.1
Name: praktikum_nlp
Version: 0.1.4
Summary: Library for Praktikum NLP UIR
Author: Praktikum NLP
Classifier: Programming Language :: Python :: 3
Classifier: License :: OSI Approved :: MIT License
Classifier: Operating System :: OS Independent
Requires-Python: >=3.10
Requires-Dist: ipython
Provides-Extra: ollamaui
Provides-Extra: ollamaui-vision
